Tamilnumbers/Tamilnumbers.py
Tamilnumbers/__init__.py
Tamilnumbers-1.0.0.dist-info/METADATA
Tamilnumbers-1.0.0.dist-info/WHEEL
Tamilnumbers-1.0.0.dist-info/top_level.txt
Tamilnumbers-1.0.0.dist-info/RECORD
