Metadata-Version: 2.1
Name: Tamilnumbers
Version: 1.0.0
Summary: A package for converting Hindu-Arabic numerals to Tamil numerals.
Home-page: https://github.com/velkadamban/Tamil-numbers-converter/
Author: Velkadamban
Author-email: velkadamban@gmail.com
License: MIT
Platform: UNKNOWN
Classifier: Development Status :: 5 - Production/Stable
Classifier: Intended Audience :: Developers
Classifier: License :: OSI Approved :: MIT License
Classifier: Operating System :: OS Independent
Classifier: Programming Language :: Python :: 3
